invex/__init__.py
invex/invex.py
invex-1.1.0.dist-info/LICENSE
invex-1.1.0.dist-info/METADATA
invex-1.1.0.dist-info/WHEEL
invex-1.1.0.dist-info/entry_points.txt
invex-1.1.0.dist-info/top_level.txt
invex-1.1.0.dist-info/RECORD
