Metadata-Version: 2.1
Name: invex
Version: 1.1.0
Summary: A lightweight inventory management system built with python
Author-email: Alex Curtis <alex@curtises.net>
Project-URL: Homepage, https://github.com/tripalc/invex
Project-URL: Bug Tracker, https://github.com/tripalc/invex/issues
Classifier: Programming Language :: Python :: 3
Classifier: License :: OSI Approved :: MIT License
Classifier: Operating System :: OS Independent
Requires-Python: >=3.7
License-File: LICENSE
